flow_monitor/__init__.py
flow_monitor/flow_monitor.py
flow_monitor-0.2.0.dist-info/METADATA
flow_monitor-0.2.0.dist-info/WHEEL
flow_monitor-0.2.0.dist-info/entry_points.txt
flow_monitor-0.2.0.dist-info/top_level.txt
flow_monitor-0.2.0.dist-info/RECORD
